flask_wiz/__init__.py
flask_wiz/boilerplate.py
flask_wiz/cli.py
flask_wiz-1.9.3.dist-info/METADATA
flask_wiz-1.9.3.dist-info/WHEEL
flask_wiz-1.9.3.dist-info/entry_points.txt
flask_wiz-1.9.3.dist-info/top_level.txt
flask_wiz-1.9.3.dist-info/RECORD
