Metadata-Version: 2.1
Name: flask-wiz
Version: 1.9.3
Author: Krish Soni
Requires-Dist: flask
Requires-Dist: click
Requires-Dist: Flask
